language_formatters_pre_commit_hooks/__init__.py
language_formatters_pre_commit_hooks/google_java_formatter.version
language_formatters_pre_commit_hooks/ktfmt.version
language_formatters_pre_commit_hooks/ktlint.version
language_formatters_pre_commit_hooks/palantir.version
language_formatters_pre_commit_hooks/pre_conditions.py
language_formatters_pre_commit_hooks/pretty_format_golang.py
language_formatters_pre_commit_hooks/pretty_format_ini.py
language_formatters_pre_commit_hooks/pretty_format_java.py
language_formatters_pre_commit_hooks/pretty_format_kotlin.py
language_formatters_pre_commit_hooks/pretty_format_rust.py
language_formatters_pre_commit_hooks/pretty_format_toml.py
language_formatters_pre_commit_hooks/pretty_format_yaml.py
language_formatters_pre_commit_hooks/utils.py
language_formatters_pre_commit_hooks-2.16.0.dist-info/licenses/LICENSE
language_formatters_pre_commit_hooks-2.16.0.dist-info/METADATA
language_formatters_pre_commit_hooks-2.16.0.dist-info/WHEEL
language_formatters_pre_commit_hooks-2.16.0.dist-info/entry_points.txt
language_formatters_pre_commit_hooks-2.16.0.dist-info/top_level.txt
language_formatters_pre_commit_hooks-2.16.0.dist-info/RECORD
