Metadata-Version: 2.4
Name: language_formatters_pre_commit_hooks
Version: 2.16.0
Summary: List of pre-commit hooks meant to format your source code.
Home-page: https://github.com/macisamuele/language-formatters-pre-commit-hooks
Author: Samuele Maci
Author-email: macisamuele@gmail.com
License: Apache License 2.0
Classifier: License :: OSI Approved :: Apache Software License
Classifier: Operating System :: OS Independent
Classifier: Programming Language :: Python :: 3
Classifier: Programming Language :: Python :: 3.10
Classifier: Programming Language :: Python :: 3.11
Classifier: Programming Language :: Python :: 3.12
Classifier: Programming Language :: Python :: 3.13
Classifier: Programming Language :: Python :: 3.14
Classifier: Programming Language :: Python :: Implementation :: CPython
Classifier: Programming Language :: Python :: Implementation :: PyPy
Requires-Python: >=3.10
License-File: LICENSE
Requires-Dist: config_formatter
Requires-Dist: packaging
Requires-Dist: requests
Requires-Dist: ruamel.yaml
Requires-Dist: toml-sort>=0.22.0
Dynamic: license-file
